aiotime/__init__.py
aiotime/fast_forward.py
tests/__init__.py
tests/test_aiotime.py
aiotime-0.1.0.dist-info/LICENSE
aiotime-0.1.0.dist-info/METADATA
aiotime-0.1.0.dist-info/WHEEL
aiotime-0.1.0.dist-info/top_level.txt
aiotime-0.1.0.dist-info/RECORD
