Metadata-Version: 2.1
Name: aiotime
Version: 0.1.0
Summary: Test helper for controlling the asyncio event loop's internal clock
Home-page: https://github.com/arseniybanayev/aiotime
Author: Arseniy Banayev
Author-email: arseniy.banayev@gmail.com
License: UNKNOWN
Keywords: asyncio async time sleep
Platform: UNKNOWN
Classifier: Programming Language :: Python :: 3.6
Classifier: Development Status :: 4 - Beta
Classifier: License :: OSI Approved :: MIT License
Classifier: Natural Language :: English
Classifier: Operating System :: OS Independent
Requires-Python: >=3.6
